topicdb/__init__.py
topicdb/topicdberror.py
topicdb/version.py
topicdb/models/__init__.py
topicdb/models/association.py
topicdb/models/attribute.py
topicdb/models/basename.py
topicdb/models/collaborationmode.py
topicdb/models/collaborator.py
topicdb/models/datatype.py
topicdb/models/doublekeydict.py
topicdb/models/entity.py
topicdb/models/language.py
topicdb/models/map.py
topicdb/models/member.py
topicdb/models/occurrence.py
topicdb/models/topic.py
topicdb/store/__init__.py
topicdb/store/ontologymode.py
topicdb/store/retrievalmode.py
topicdb/store/topicstore.py
topic_db-2.0.5.dist-info/LICENSE
topic_db-2.0.5.dist-info/METADATA
topic_db-2.0.5.dist-info/WHEEL
topic_db-2.0.5.dist-info/top_level.txt
topic_db-2.0.5.dist-info/RECORD
