Metadata-Version: 2.1
Name: topic-db
Version: 2.0.5
Summary: TopicDB is a topic map-based graph store (using SQLite for persistence)
Home-page: https://github.com/brettkromkamp/topic-db
Author: Brett Alistair Kromkamp
Author-email: brettkromkamp@gmail.com
Project-URL: Bug Tracker, https://github.com/brettkromkamp/topic-db/issues
Classifier: Development Status :: 4 - Beta
Classifier: Intended Audience :: Developers
Classifier: License :: OSI Approved :: MIT License
Classifier: Natural Language :: English
Classifier: Programming Language :: Python :: 3
Classifier: Programming Language :: Python :: 3.7
Classifier: Programming Language :: Python :: 3.8
Classifier: Programming Language :: Python :: 3.9
Classifier: Programming Language :: Python :: 3.10
Classifier: Programming Language :: Python :: Implementation :: CPython
Classifier: Topic :: Software Development :: Libraries :: Python Modules
Requires-Python: >=3.7
License-File: LICENSE
Requires-Dist: python-slugify (>=6.1.2)
Requires-Dist: pytest (>=7.1.2)
Requires-Dist: typed-tree (>=1.0.8)
